MANIFEST.in
README.md
setup.cfg
setup.py
aws_adfs/__init__.py
aws_adfs/_duo_authenticator.py
aws_adfs/_version.py
aws_adfs/account_aliases_fetcher.py
aws_adfs/authenticator.py
aws_adfs/commands.py
aws_adfs/html_roles_fetcher.py
aws_adfs/list_profiles.py
aws_adfs/login.py
aws_adfs/prepare.py
aws_adfs/reset.py
aws_adfs/role_chooser.py
aws_adfs/roles_assertion_extractor.py
aws_adfs_ebsco.egg-info/PKG-INFO
aws_adfs_ebsco.egg-info/SOURCES.txt
aws_adfs_ebsco.egg-info/dependency_links.txt
aws_adfs_ebsco.egg-info/entry_points.txt
aws_adfs_ebsco.egg-info/requires.txt
aws_adfs_ebsco.egg-info/top_level.txt
test/test_account_aliases_fetcher.py
test/test_assertion_extractor.py
test/test_authenticator.py
test/test_click_parses_command_line_arguments.py
test/test_config_preparation.py
test/test_fetch_html_encoded_roles.py
test/test_role_chooser.py