Metadata-Version: 1.1
Name: aws-adfs-ebsco
Version: 0.3.7-1
Summary: AWS Cli authenticator via ADFS - small command-line tool to authenticate via ADFS and assume chosen role
Home-page: https://github.com/gpreston2/aws-adfs
Author: Venth
Author-email: artur.krysiak.warszawa@gmail.com
License: UNKNOWN
Keywords: aws adfs console tool
Platform: UNKNOWN
Classifier: Development Status :: 5 - Production/Stable
Classifier: Environment :: Console
Classifier: Intended Audience :: End Users/Desktop
Classifier: Intended Audience :: Developers
Classifier: Intended Audience :: System Administrators
Classifier: License :: OSI Approved :: Python Software Foundation License
Classifier: Operating System :: MacOS :: MacOS X
Classifier: Operating System :: Microsoft :: Windows
Classifier: Operating System :: POSIX
Classifier: Programming Language :: Python
